{
  "anonymousOrders": [
    {
      "0": {
        "numePrenume": "Burgeri",
        "address": "adasd",
        "phoneNumber": "123123",
        "cardNumber": "12312",
        "cardOwnerName": "123123",
        "expireDate": "12312",
        "cvc": "312",
        "ordered_products": [
          "2",
          "2",
          "2",
          "2",
          "2"
        ],
        "creation_date": "2024-05-21T17:07:01.387Z"
      },
      "id": "58aa"
    },
    {
      "0": {
        "0": {
          "numePrenume": "Burgeri",
          "address": "adasd",
          "phoneNumber": "123123",
          "cardNumber": "12312",
          "cardOwnerName": "123123",
          "expireDate": "12312",
          "cvc": "312",
          "ordered_products": [
            "2",
            "2",
            "2",
            "2",
            "2"
          ],
          "creation_date": "2024-05-21T17:07:01.387Z"
        },
        "id": "58aa"
      },
      "1": {
        "numePrenume": "Burgeri",
        "address": "adasd",
        "phoneNumber": "123123",
        "cardNumber": "12312",
        "cardOwnerName": "123121233",
        "expireDate": "12312",
        "cvc": "312",
        "ordered_products": [],
        "creation_date": "2024-05-21T17:07:29.786Z"
      },
      "id": "8051"
    },
    {
      "0": {
        "0": {
          "numePrenume": "Burgeri",
          "address": "adasd",
          "phoneNumber": "123123",
          "cardNumber": "12312",
          "cardOwnerName": "123123",
          "expireDate": "12312",
          "cvc": "312",
          "ordered_products": [
            "2",
            "2",
            "2",
            "2",
            "2"
          ],
          "creation_date": "2024-05-21T17:07:01.387Z"
        },
        "id": "58aa"
      },
      "1": {
        "0": {
          "0": {
            "numePrenume": "Burgeri",
            "address": "adasd",
            "phoneNumber": "123123",
            "cardNumber": "12312",
            "cardOwnerName": "123123",
            "expireDate": "12312",
            "cvc": "312",
            "ordered_products": [
              "2",
              "2",
              "2",
              "2",
              "2"
            ],
            "creation_date": "2024-05-21T17:07:01.387Z"
          },
          "id": "58aa"
        },
        "1": {
          "numePrenume": "Burgeri",
          "address": "adasd",
          "phoneNumber": "123123",
          "cardNumber": "12312",
          "cardOwnerName": "123121233",
          "expireDate": "12312",
          "cvc": "312",
          "ordered_products": [],
          "creation_date": "2024-05-21T17:07:29.786Z"
        },
        "id": "8051"
      },
      "2": {
        "numePrenume": "12312",
        "address": "12312",
        "phoneNumber": "312312",
        "cardNumber": "132312",
        "cardOwnerName": "3123",
        "expireDate": "12312",
        "cvc": "12312",
        "ordered_products": [
          "2",
          "2",
          "2"
        ],
        "creation_date": "2024-05-21T17:09:58.570Z"
      },
      "id": "f567"
    },
    {
      "0": {
        "0": {
          "numePrenume": "Burgeri",
          "address": "adasd",
          "phoneNumber": "123123",
          "cardNumber": "12312",
          "cardOwnerName": "123123",
          "expireDate": "12312",
          "cvc": "312",
          "ordered_products": [
            "2",
            "2",
            "2",
            "2",
            "2"
          ],
          "creation_date": "2024-05-21T17:07:01.387Z"
        },
        "id": "58aa"
      },
      "1": {
        "0": {
          "0": {
            "numePrenume": "Burgeri",
            "address": "adasd",
            "phoneNumber": "123123",
            "cardNumber": "12312",
            "cardOwnerName": "123123",
            "expireDate": "12312",
            "cvc": "312",
            "ordered_products": [
              "2",
              "2",
              "2",
              "2",
              "2"
            ],
            "creation_date": "2024-05-21T17:07:01.387Z"
          },
          "id": "58aa"
        },
        "1": {
          "numePrenume": "Burgeri",
          "address": "adasd",
          "phoneNumber": "123123",
          "cardNumber": "12312",
          "cardOwnerName": "123121233",
          "expireDate": "12312",
          "cvc": "312",
          "ordered_products": [],
          "creation_date": "2024-05-21T17:07:29.786Z"
        },
        "id": "8051"
      },
      "2": {
        "0": {
          "0": {
            "numePrenume": "Burgeri",
            "address": "adasd",
            "phoneNumber": "123123",
            "cardNumber": "12312",
            "cardOwnerName": "123123",
            "expireDate": "12312",
            "cvc": "312",
            "ordered_products": [
              "2",
              "2",
              "2",
              "2",
              "2"
            ],
            "creation_date": "2024-05-21T17:07:01.387Z"
          },
          "id": "58aa"
        },
        "1": {
          "0": {
            "0": {
              "numePrenume": "Burgeri",
              "address": "adasd",
              "phoneNumber": "123123",
              "cardNumber": "12312",
              "cardOwnerName": "123123",
              "expireDate": "12312",
              "cvc": "312",
              "ordered_products": [
                "2",
                "2",
                "2",
                "2",
                "2"
              ],
              "creation_date": "2024-05-21T17:07:01.387Z"
            },
            "id": "58aa"
          },
          "1": {
            "numePrenume": "Burgeri",
            "address": "adasd",
            "phoneNumber": "123123",
            "cardNumber": "12312",
            "cardOwnerName": "123121233",
            "expireDate": "12312",
            "cvc": "312",
            "ordered_products": [],
            "creation_date": "2024-05-21T17:07:29.786Z"
          },
          "id": "8051"
        },
        "2": {
          "numePrenume": "12312",
          "address": "12312",
          "phoneNumber": "312312",
          "cardNumber": "132312",
          "cardOwnerName": "3123",
          "expireDate": "12312",
          "cvc": "12312",
          "ordered_products": [
            "2",
            "2",
            "2"
          ],
          "creation_date": "2024-05-21T17:09:58.570Z"
        },
        "id": "f567"
      },
      "3": {
        "numePrenume": "12312",
        "address": "12312",
        "phoneNumber": "312312",
        "cardNumber": "132312",
        "cardOwnerName": "3123",
        "expireDate": "12312",
        "cvc": "12312",
        "ordered_products": [],
        "creation_date": "2024-05-21T17:10:11.553Z"
      },
      "id": "3aff"
    }
  ],
  "users": [
    {
      "id": "bbd9",
      "username": "ovidiu",
      "email": "ovidiu@gmail.com",
      "password": "ovidiu",
      "permission": "client",
      "basket": [],
      "orders": [],
      "cards": [],
      "locations": []
    }
  ],
  "products": [
    {
      "id": "2",
      "title": "Pizza Quattro Carni",
      "category": "Pizza",
      "price": 41.9,
      "description": "blat pizza, mix branzeturi (mozzarella, cascaval), sos de rosii dulce, bacon, salam demisec, piept pui, sunca de porc, salam vara - 900g / 1250g Alergeni: gluten, lactoza, telina, soia, mustar",
      "date": "2024-05-12T12:00:00Z",
      "promotion": false,
      "promotionPrice": "35",
      "availability": true
    },
    {
      "id": "3",
      "title": "Pizza Capricioasa",
      "category": "Pizza",
      "price": 41.9,
      "description": "blat pizza, mix branzeturi (mozzarella, cascaval), sos de rosii dulce, sunca de porc, salam de vara, ciuperci - 700g / 1000g Alergeni: gluten, lactoza, soia, telina",
      "date": "2024-05-10T12:00:00Z",
      "promotion": true,
      "promotionPrice": "35",
      "availability": true
    },
    {
      "id": "4",
      "title": "Pizza Ovidiu",
      "category": "Pizza",
      "price": 48.9,
      "description": "blat pizza, mix branzeturi (mozzarella, cascaval), sos de rosii dulce, salam de cerb, ceapa verde, ciuperci, ulei vegetal de masline aromatizat cu trufe, mix de ulei(masline, floarea soarelui) - 750g / 1100g Alergeni: gluten, lactoza, mustar",
      "date": "2024-05-12T12:00:00Z",
      "promotion": true,
      "promotionPrice": "35",
      "availability": true
    },
    {
      "id": "5",
      "title": "Pizza Quattro Stagioni",
      "category": "Pizza",
      "price": 44.9,
      "description": "blat pizza, mix branzeturi (mozzarella, cascaval), sos de rosii dulce, sunca de porc, salam vara, ardei gras, ciuperci - 700g / 1050g Alergeni: gluten, lactoza, soia, telina",
      "date": "2024-05-10T12:00:00Z",
      "promotion": true,
      "promotionPrice": "35",
      "availability": true
    },
    {
      "id": "7",
      "title": "Pizza Mexicana",
      "category": "Pizza",
      "price": 53.4,
      "description": "blat pizza, mix branzeturi (mozzarella, cascaval), sos de rosii dulce, branza brie, fasole, mix de branza tare (parmiggiano, grana padano) nachos - 700g / 1000g Alergeni: lactoza, gluten, ou",
      "date": "2024-05-10T12:00:00Z",
      "promotion": true,
      "promotionPrice": "35",
      "availability": true
    },
    {
      "id": "8",
      "title": "Pizza Pollo",
      "category": "Pizza",
      "price": 34.9,
      "description": "blat pizza, mix branzeturi (mozzarella, cascaval), piept pui, sos de rosii dulce, rosii bruschette, masline kalamata - 750g / 1050g Alergeni: gluten, lactoza, mustar",
      "date": "2024-05-14T12:00:00Z",
      "promotion": true,
      "promotionPrice": "35",
      "availability": true
    },
    {
      "id": "9",
      "title": "Spaghetti Carbonara",
      "category": "Paste",
      "price": 37.9,
      "description": "spaghette, smantana, bacon, mix de ulei (masline, floarea soarelui), mix de branza tare (parmiggiano, grana padano), sare, piper - 400g Alergeni: gluten, lactoza, ou",
      "date": "2024-05-10T12:00:00Z",
      "promotion": true,
      "promotionPrice": "35",
      "availability": true
    },
    {
      "id": "10",
      "title": "Spaghetti Bolognese",
      "category": "Paste",
      "price": 35.9,
      "description": "spaghette, sos bolognese (sos de rosii dulce, carne tocata (carne porc, carne vita) ceapa, morcov, telina, pasta de tomate), sos napoli, mix de branza tare (parmiggiano, grana padano) - 400g Alergeni: gluten, telina, lactoza, ou",
      "date": "2024-05-10T12:00:00Z",
      "promotion": true,
      "promotionPrice": "35",
      "availability": true
    },
    {
      "id": "11",
      "title": "Penne Arabicate",
      "category": "Paste",
      "price": 32.9,
      "description": "PICANT - penne, sos napoli, bacon, sunca de pui, supa de legume, mix de ulei (masline, floarea soarelui), mix de branza tare (parmiggiano, grana padano), ardei iute, sare, piper - 400g Alergeni: gluten, soia, telina, lactoza, ou",
      "date": "2024-05-17T12:00:00Z",
      "promotion": true,
      "promotionPrice": "35",
      "availability": true
    },
    {
      "id": "12",
      "title": "Penne cu Creveti",
      "category": "Paste",
      "price": 47.9,
      "description": "penne, creveti, sos napoli, smantana, supa de legume, unt, mix de branza tare (parmiggiano, grana padano), vin alb, patrunjel, sare, piper - 400g Alergeni: crustacee, lactoza, gluten, ou, telina, sulfiti",
      "date": "2024-05-10T17:00:00Z",
      "promotion": true,
      "promotionPrice": "35",
      "availability": true
    },
    {
      "id": "14",
      "title": "Burger",
      "category": "Burgeri",
      "price": 35.9,
      "description": "chifla burger de casa, carne de vita, sos burger, castraveti in otet, branza gouda, mix salata, bacon - 350g Alergeni: gluten, lactoza, ou, mustar, susan",
      "date": "2024-05-10T12:00:00Z",
      "promotion": true,
      "promotionPrice": "35",
      "availability": true
    },
    {
      "id": "15",
      "title": "Crispyburger",
      "category": "Burgeri",
      "price": 33.9,
      "description": "chifla burger de casa, piept de pui crispy (piept de pui marinat picant, ulei vegetal de floarea soarelui, faina alba de grau, ou), sos cocktail, salata de varza cu patrunjel, castraveti in otet - 360g Alergeni: gluten, lactoza, ou, mustar, susan",
      "date": "2024-05-10T12:00:00Z",
      "promotion": true,
      "promotionPrice": "35",
      "availability": true
    },
    {
      "id": "16",
      "title": "Ciorba de vacuta",
      "category": "Ciorbe",
      "price": 24.9,
      "description": "cartofi, carne vita, rosii, amestec legume (morcov, gulii, pastai, mazare), ardei gras, ceapa, telina, supa vita, bors, apa, ulei vegetal de floarea-soarelui, patrunjel si leustean verde - 380g Alergeni: gluten, telina",
      "date": "2024-05-10T12:00:00Z",
      "promotion": true,
      "promotionPrice": "35",
      "availability": true
    },
    {
      "id": "17",
      "title": "Ciorba radauteana",
      "category": "Ciorbe",
      "price": 24.9,
      "description": "supa de pasare (carne de pui, ceapa, telina, morcov), piept de pui, smantana, galbenua de ou, zeama de lamaie, ulei vegetal de floarea-soarelui, sare - 380g Alergeni: telina, ou, lactoza",
      "date": "2024-05-10T12:00:00Z",
      "promotion": true,
      "promotionPrice": "35",
      "availability": true
    },
    {
      "id": "18",
      "title": "Supa crema de legume",
      "category": "Ciorbe",
      "price": 23.9,
      "description": "supa de legume (morcov, ceapa, telina), cartofi, morcovi, ceapa, smantana, ardei gras, pastarnac, telina, unt, sare / crutoane - 380g / 50g Alergeni: telina, gluten, lactoza",
      "date": "2024-05-10T12:00:00Z",
      "promotion": true,
      "promotionPrice": "35",
      "availability": true
    },
    {
      "id": "19",
      "title": "Ciorba de legume",
      "category": "Ciorbe",
      "price": 18.9,
      "description": "cartofi, rosii, sfecla roșie, amestec legume (morcov, gulii, pastai, mazare), ceapa, telina, apa, bors, patrunjel si leustean verde, ulei vegetal de floarea-soarelui, sare - 380g Alergeni: gluten, telina",
      "date": "2024-05-10T17:00:00Z",
      "promotion": true,
      "promotionPrice": "35",
      "availability": true
    },
    {
      "id": "20",
      "title": "Chiftelute de Pui",
      "category": "Preparate",
      "price": 17.9,
      "description": "piept de pui cartofi, ceapa, morcov, ou uht patrunjel, pesmet, usturoi, ulei vegetal de floarea soarelui, sare, piper - 200g Alergeni: ou, glutena",
      "date": "2024-05-10T12:00:00Z",
      "promotion": true,
      "promotionPrice": "35",
      "availability": true
    },
    {
      "id": "21",
      "title": "Tochitura",
      "category": "Preparate",
      "price": 48.9,
      "description": "tochitura (spata de porc, piept de porc, carnati semiafumati, cimbru, untura, vin alb, usturoi, supa de legume, mujdei, sare, piper), ou, ulei vegetal de floarea soarelui, branza burduf, mamaliguta - 550g Alergeni: lactoza, ou, telina, sulfiti, soia",
      "date": "2024-05-10T12:00:00Z",
      "promotion": true,
      "promotionPrice": "35",
      "availability": true
    },
    {
      "id": "23",
      "title": "Cotlet la gratar",
      "category": "Preparate",
      "price": 29.9,
      "description": "cotlet de porc, condimente (paprika afumata, mustar pudra, sare, piper, usturoi), ulei vegetal de floarea soarelui - 200g Alergeni: mustar",
      "date": "2024-05-10T12:00:00Z",
      "promotion": true,
      "promotionPrice": "35",
      "availability": true
    },
    {
      "id": "26",
      "title": "Piure de cartofi",
      "category": "Garnituri",
      "price": 12.9,
      "description": "cartofi fulgi, unt, apa - 200g Alergeni: lactoza",
      "date": "2024-05-10T12:00:00Z",
      "promotion": true,
      "promotionPrice": "35",
      "availability": true
    },
    {
      "id": "27",
      "title": "Salata coleslaw",
      "category": "Garnituri",
      "price": 12.9,
      "description": "varză alba, varza rosie, sos maioneza, morcov, ceapa, otet, zahar, sare - 150g Alergeni: ou, mustar, lactoza",
      "date": "2024-05-10T12:00:00Z",
      "promotion": true,
      "promotionPrice": "35",
      "availability": true
    },
    {
      "id": "29",
      "title": "Sos Tzatziki",
      "category": "Garnituri",
      "price": 6.5,
      "description": "LACTO-VEGETARIANA - castraveti verzi, usturoi, iaurt, marar - 100g Alergeni: lactoza",
      "date": "2024-05-10T12:00:00Z",
      "promotion": true,
      "promotionPrice": "35",
      "availability": true
    },
    {
      "id": "30",
      "title": "Sos dulce",
      "category": "Garnituri",
      "price": 4.5,
      "description": "roșii decojite, ulei de măsline, zahăr, sare, sos de busuioc, dextroza - 100g",
      "date": "2024-05-10T12:00:00Z",
      "promotion": true,
      "promotionPrice": "35",
      "availability": true
    },
    {
      "id": "31",
      "title": "Sos picant",
      "category": "Garnituri",
      "price": 4.9,
      "description": "roșii decojite, ulei de măsline, zahăr, sare, sos de busuioc, chilly, dextroza - 100g",
      "date": "2024-05-10T12:00:00Z",
      "promotion": true,
      "promotionPrice": "35",
      "availability": true
    },
    {
      "id": "33",
      "title": "Ochiuri",
      "category": "Mic dejun",
      "price": 13.9,
      "description": "oua, ulei vegetal de floarea soarelui - 100g Alergeni: ou",
      "date": "2024-05-10T12:00:00Z",
      "promotion": true,
      "promotionPrice": "35",
      "availability": true
    },
    {
      "id": "34",
      "title": "Omleta",
      "category": "Mic dejun",
      "price": 16.9,
      "description": "oua, ulei vegetal de floarea soarelui - 100g Alergeni: ou",
      "date": "2024-05-10T12:00:00Z",
      "promotion": true,
      "promotionPrice": "35",
      "availability": true
    },
    {
      "id": "35",
      "title": "Cascaval pane",
      "category": "Mic dejun",
      "price": 24,
      "description": "cascaval, ou, pesmet, faina alba de grau, ulei vegetal de floarea soarelui - 150g Alergeni: ou, lactoză, gluten",
      "date": "2024-05-10T12:00:00Z",
      "promotion": true,
      "promotionPrice": "35",
      "availability": true
    },
    {
      "id": "36",
      "title": "Aqua Carpatica Apa minerala",
      "category": "Bauturi",
      "price": 6,
      "description": "",
      "date": "2024-05-10T12:00:00Z",
      "promotion": true,
      "promotionPrice": "35",
      "availability": true
    },
    {
      "id": "37",
      "title": "Aqua Carpatica Plata 0.750l",
      "category": "Bauturi",
      "price": 9,
      "description": "",
      "date": "2024-05-10T12:00:00Z",
      "promotion": true,
      "promotionPrice": "35",
      "availability": true
    },
    {
      "id": "38",
      "title": "Pepsi 0.5L",
      "category": "Bauturi",
      "price": 9,
      "description": "",
      "date": "2024-05-10T12:00:00Z",
      "promotion": true,
      "promotionPrice": "35",
      "availability": true
    },
    {
      "id": "39",
      "title": "Tuborg Sticla 0.33L",
      "category": "Bauturi",
      "price": 7,
      "description": "",
      "date": "2024-05-10T12:00:00Z",
      "promotion": true,
      "promotionPrice": "35",
      "availability": true
    },
    {
      "id": "40",
      "title": "Carlsberg Sticla 0.33L",
      "category": "Bauturi",
      "price": 9.5,
      "description": "",
      "date": "2024-05-10T12:00:00Z",
      "promotion": true,
      "promotionPrice": "35",
      "availability": true
    },
    {
      "id": "41",
      "title": "Tiramisu",
      "category": "Deserturi",
      "price": 16.9,
      "description": "mascarpone, ou, crema vegetala, zahar, piscoturi, amaretto, cafea, cacao - 120g Alergeni: gluten, lactoza, soia, ou",
      "date": "2024-05-10T12:00:00Z",
      "promotion": true,
      "promotionPrice": "35",
      "availability": true
    },
    {
      "id": "42",
      "title": "Savarina",
      "category": "Deserturi",
      "price": 11.9,
      "description": "coji savarina (zahar, faina alba din grau, ulei vegetal de floarea soarelui, ou, drojdie, arome (lămâie, rom, vanilie)), crema vegetala, iaurt, smantana, glazura capsuni, zahar pudra, zahar vanilat - 210g Alergeni: gluten, lactoza, soia, ou",
      "date": "2024-05-10T12:00:00Z",
      "promotion": true,
      "promotionPrice": "35",
      "availability": true
    }
  ]
}